llm_qualitative_sort/__init__.py
llm_qualitative_sort/events.py
llm_qualitative_sort/metrics.py
llm_qualitative_sort/models.py
llm_qualitative_sort/sorter.py
llm_qualitative_sort/utils.py
llm_qualitative_sort/cache/__init__.py
llm_qualitative_sort/output/__init__.py
llm_qualitative_sort/output/calculators.py
llm_qualitative_sort/output/formatters.py
llm_qualitative_sort/output/models.py
llm_qualitative_sort/providers/__init__.py
llm_qualitative_sort/providers/base.py
llm_qualitative_sort/providers/errors.py
llm_qualitative_sort/providers/langchain.py
llm_qualitative_sort/providers/mock.py
llm_qualitative_sort/tournament/__init__.py
llm_qualitative_sort/tournament/swiss_system.py
llm_qualitative_sort-1.1.0.dist-info/licenses/LICENSE
llm_qualitative_sort-1.1.0.dist-info/METADATA
llm_qualitative_sort-1.1.0.dist-info/WHEEL
llm_qualitative_sort-1.1.0.dist-info/top_level.txt
llm_qualitative_sort-1.1.0.dist-info/RECORD
