Metadata-Version: 2.4
Name: llm-qualitative-sort
Version: 1.1.0
Summary: LLM-based qualitative sorting using Swiss-system tournament
Author: T.Ishimine
License: MIT
Project-URL: Homepage, https://github.com/TomokiIshimine/llm-qualitative-sort
Project-URL: Repository, https://github.com/TomokiIshimine/llm-qualitative-sort
Project-URL: Issues, https://github.com/TomokiIshimine/llm-qualitative-sort/issues
Classifier: Development Status :: 5 - Production/Stable
Classifier: Intended Audience :: Developers
Classifier: License :: OSI Approved :: MIT License
Classifier: Programming Language :: Python :: 3
Classifier: Programming Language :: Python :: 3.10
Classifier: Programming Language :: Python :: 3.11
Classifier: Programming Language :: Python :: 3.12
Requires-Python: >=3.10
License-File: LICENSE
Requires-Dist: langchain-core>=0.3.0
Requires-Dist: pydantic>=2.0.0
Requires-Dist: scipy>=1.10.0
Provides-Extra: dev
Requires-Dist: pytest>=7.0.0; extra == "dev"
Requires-Dist: pytest-asyncio>=0.21.0; extra == "dev"
Dynamic: license-file
